README.md
setup.py
cheesefactory_docker/__init__.py
cheesefactory_docker.egg-info/PKG-INFO
cheesefactory_docker.egg-info/SOURCES.txt
cheesefactory_docker.egg-info/dependency_links.txt
cheesefactory_docker.egg-info/requires.txt
cheesefactory_docker.egg-info/top_level.txt