Metadata-Version: 2.1
Name: cheesefactory-docker
Version: 0.6
Summary: A helper for creating Docker containers and working them.
Home-page: https://bitbucket.org/hellsgrannies/cheesefactory-docker
Author: Todd Salazar
Author-email: unixsal@yahoo.com
License: UNKNOWN
Keywords: cheesefactory docker secrets configs development
Platform: UNKNOWN
Classifier: Development Status :: 4 - Beta
Classifier: Intended Audience :: Developers
Classifier: License :: OSI Approved :: BSD License
Classifier: Programming Language :: Python :: 3.6
Classifier: Programming Language :: Python :: 3.7
Classifier: Programming Language :: Python :: 3.8
